license_sdk_python/__init__.py
license_sdk_python/client.py
license_sdk_python/test.py
license_sdk_python-0.0.8.dist-info/METADATA
license_sdk_python-0.0.8.dist-info/WHEEL
license_sdk_python-0.0.8.dist-info/top_level.txt
license_sdk_python-0.0.8.dist-info/RECORD
