Metadata-Version: 2.2
Name: license-sdk-python
Version: 0.0.8
Summary: license sdk python
Home-page: https://github.com/qiaoyk666/license-sdk-python.git
Author: qiao
Author-email: 979146919@qq.com
License: MIT Licence
Keywords: pip,license,sdk
Platform: any
Requires-Dist: requests
Requires-Dist: cryptography
Requires-Dist: websocket-client
Requires-Dist: pycryptodome
Dynamic: author
Dynamic: author-email
Dynamic: home-page
Dynamic: keywords
Dynamic: license
Dynamic: platform
Dynamic: requires-dist
Dynamic: summary
